examples/__init__.py
examples/capsule.py
examples/colors.py
examples/gpu_catb.py
examples/gpu_lgb.py
examples/gpu_xgb.py
examples/inputs.py
examples/pandas_profiling_eda.py
examples/report.py
examples/sender.py
examples/super.py
examples/textcnn.py
examples/textcnn_fasttext.py
examples/xlearn_.py
examples/yaml.yaml
examples/yaml_demo.py
examples/yaml_demo.yaml
examples/yaml_temp.yml
examples/BaiduApi/newsSummary.py
examples/HashTrick/__init__.py
examples/HashTrick/hash_function.py
examples/HashTrick/hashcode.py
examples/LIBSVM/__init__.py
examples/LIBSVM/xgb.py
examples/LoadData/__init__.py
examples/LoadData/pytorch.py
examples/Milvus/__init__.py
examples/Milvus/demo.py
examples/accelerate/__init__.py
examples/accelerate/numba.py
examples/args/__init__.py
examples/args/args.py
examples/args/args_run.py
examples/cache/__init__.py
examples/cache/cache.py
examples/cangtoushi/__init__.py
examples/cangtoushi/main.py
examples/client/__init__.py
examples/client/rpc.py
examples/crf/__init__.py
examples/crf/data.py
examples/deploy/run.sh
examples/deploy/sanic&pyspark.py
examples/deploy/train_lr.py
examples/fm/__init__.py
examples/fm/xlearn_.py
examples/ganhuo/干货.md
examples/git/README.md
examples/git/__init__.py
examples/json/__init__.py
examples/json/read_json.py
examples/keras/__init__.py
examples/keras/wandb_example.py
examples/locust_qps/__init__.py
examples/locust_qps/qps.py
examples/ml/__init__.py
examples/ml/featureSelector.py
examples/ml/h2o.py
examples/ml/imbalanced__learn.py
examples/nlp/__init__.py
examples/nlp/stanford.py
examples/opt/__init__.py
examples/opt/bayes_opt_demo.py
examples/opt/lgb.py
examples/opt/params.yml
examples/opt/sk_cv.py
examples/pypy/cut.py
examples/pypy/get.sh
examples/pypy/kaggle.py
examples/pypy/pypytest.py
examples/qps/__init__.py
examples/qps/post.json
examples/qps/request.txt
examples/qps/result.txt
examples/qps/siege.sh
examples/sanic/__init__.py
tql-2020.11.11.15.32.5.dist-info/METADATA
tql-2020.11.11.15.32.5.dist-info/RECORD
tql-2020.11.11.15.32.5.dist-info/WHEEL
tql-2020.11.11.15.32.5.dist-info/entry_points.txt
tql-2020.11.11.15.32.5.dist-info/top_level.txt
