Metadata-Version: 2.1
Name: tql
Version: 2020.11.11.15.32.5
Summary: description
Home-page: https://github.com/Jie-Yuan/tql-Python
Author: JieYuan
Author-email: 313303303@qq.com
Maintainer: JieYuan
Maintainer-email: 313303303@qq.com
License: MIT
Keywords: tool wheel,yuanjie,utils
Platform: all
Classifier: Operating System :: OS Independent
Classifier: Intended Audience :: Developers
Classifier: License :: OSI Approved :: MIT License
Classifier: Programming Language :: Python :: 3.6
Classifier: Programming Language :: Python :: Implementation
Requires-Python: >=3.5
Requires-Dist: tqdm
Requires-Dist: thefuck
Requires-Dist: wrapt
Requires-Dist: emoji
Requires-Dist: pytz
Requires-Dist: pybind11
Requires-Dist: joblib
Requires-Dist: pydot
Requires-Dist: bs4
Requires-Dist: lxml
Requires-Dist: jieba
Requires-Dist: lightgbm
Requires-Dist: catboost
Requires-Dist: rgf-python
Requires-Dist: statsmodels
Requires-Dist: gensim
Requires-Dist: missingno
Requires-Dist: pandas-summary
Requires-Dist: scikit-learn
Requires-Dist: scikit-plot
Requires-Dist: tables
Requires-Dist: eli5
Requires-Dist: shap
Requires-Dist: seaborn
Requires-Dist: pyecharts
Requires-Dist: jovian
Requires-Dist: graphviz
Requires-Dist: gpustat
